byted_overpass_bytegraph_cube_event/__init__.py
byted_overpass_bytegraph_cube_event-0.0.1.dist-info/METADATA
byted_overpass_bytegraph_cube_event-0.0.1.dist-info/WHEEL
byted_overpass_bytegraph_cube_event-0.0.1.dist-info/top_level.txt
byted_overpass_bytegraph_cube_event-0.0.1.dist-info/RECORD
